setup.py
bsc_probability/__init__.py
bsc_probability.egg-info/PKG-INFO
bsc_probability.egg-info/SOURCES.txt
bsc_probability.egg-info/dependency_links.txt
bsc_probability.egg-info/not-zip-safe
bsc_probability.egg-info/top_level.txt