Metadata-Version: 1.0
Name: bsc-probability
Version: 0.1
Summary: Gaussian and Binomial distributions
Home-page: UNKNOWN
Author: Mironas Bitinis
Author-email: someemal@gmail.com
License: UNKNOWN
Platform: UNKNOWN
